symbiosis_api_client/__about__.py
symbiosis_api_client/__init__.py
symbiosis_api_client/base_swapping.py
symbiosis_api_client/check_latest_commit.py
symbiosis_api_client/client.py
symbiosis_api_client/exceptions.py
symbiosis_api_client/limiter.py
symbiosis_api_client/load_static_chain_data.py
symbiosis_api_client/mainnet.json
symbiosis_api_client/model_adapter.py
symbiosis_api_client/models.py
symbiosis_api_client/py.typed
symbiosis_api_client/request_client.py
symbiosis_api_client/static_models.py
symbiosis_api_client/swagger.json
symbiosis_api_client-0.0.9.dist-info/METADATA
symbiosis_api_client-0.0.9.dist-info/WHEEL
symbiosis_api_client-0.0.9.dist-info/licenses/LICENSE
symbiosis_api_client-0.0.9.dist-info/RECORD
