Metadata-Version: 2.4
Name: symbiosis-api-client
Version: 0.0.9
Summary: Python client for api.symbiosis.finance
Project-URL: Documentation, https://symbiosis-api-client.readthedocs.io/en/latest/
Project-URL: Issues, https://github.com/garootman/symbiosis-api-client/issues
Project-URL: Source, https://github.com/garootman/symbiosis-api-client
Author-email: garootman <dksg87@gmail.com>
License-Expression: MIT
License-File: LICENSE
Classifier: Development Status :: 2 - Pre-Alpha
Classifier: Programming Language :: Python
Classifier: Programming Language :: Python :: 3.10
Classifier: Programming Language :: Python :: 3.11
Classifier: Programming Language :: Python :: 3.12
Classifier: Programming Language :: Python :: 3.13
Classifier: Programming Language :: Python :: Implementation :: CPython
Classifier: Programming Language :: Python :: Implementation :: PyPy
Requires-Python: >=3.10
Requires-Dist: httpx>=0.28.1
Requires-Dist: pydantic>=2.10.6
Requires-Dist: ratelimit>=2.2.1
Requires-Dist: sphinx>=7.1.2
Provides-Extra: dev
Requires-Dist: bandit>=1.7.10; extra == 'dev'
Requires-Dist: black>=24.8.0; extra == 'dev'
Requires-Dist: mypy>=1.14.1; extra == 'dev'
Requires-Dist: pre-commit>=3.5.0; extra == 'dev'
Requires-Dist: pytest>=8.3.5; extra == 'dev'
Requires-Dist: ruff>=0.11.4; extra == 'dev'
Requires-Dist: sphinx>=7.1.2; extra == 'dev'
Requires-Dist: tox>=4.25.0; extra == 'dev'
Requires-Dist: twine>=6.1.0; extra == 'dev'
